Metadata-Version: 2.1
Name: ovos-tts-plugin-polly
Version: 0.2.1
Summary: polly tts plugin for OpenVoiceOS mycroft neon chatterbox
Home-page: https://github.com/OpenVoiceOS/ovos-tts-plugin-polly
Author: JarbasAi
Author-email: jarbasai@mailfence.com
License: Apache-2.0
Keywords: OpenVoiceOS mycroft neon chatterbox plugin tts
Platform: UNKNOWN
Classifier: Development Status :: 3 - Alpha
Classifier: Intended Audience :: Developers
Classifier: Topic :: Text Processing :: Linguistic
Classifier: License :: OSI Approved :: Apache Software License
Classifier: Programming Language :: Python :: 3
Requires-Dist: boto3
Requires-Dist: ovos-plugin-manager>=0.0.1a13
